{"type": "Feature", "id": 12515528, "properties": {"woe:id": 12515528, "woe:parent_id": 869129, "woe:name": "Dalnic Airport", "woe:placetype": 14, "woe:placetype_name": "Airport", "woe:lang": "ENG", "iso:country": "RO", "meta:provider": ["geoplanet:7.3.1", "geoplanet:7.3.2", "geoplanet:7.4.0", "geoplanet:7.4.1", "geoplanet:7.5.1", "geoplanet:7.5.2", "geoplanet:7.6.0", "geoplanet:7.8.1", "geoplanet:7.9.0", "geoplanet:7.10.0", "geoplanet:8.0.0", "woeplanet:8.0.0"], "meta:indexed": "2020-08-20T20:26:16.156995", "meta:updated": "2020-08-22T02:50:11.095821", "woe:hierarchy": {"continent": 24865675, "country": 23424933, "town": 0, "planet": 1, "county": 0, "suburb": 0, "state": 2346629, "region": 0, "localadmin": 0}, "woe:timezone_id": 28350892, "woe:hash": "u84t2ugc7zey", "woe:centroid": [26.0539, 45.9492], "geom:latitude": 45.9492, "geom:longitude": 26.0539, "geom:hash": "u84t2ugc7zey", "woe:latitude": 45.9492, "geom:centroid": [26.0539, 45.9492], "woe:longitude": 26.0539, "woe:repo": "woeplanet-airport-ro"}, "geometry": {"coordinates": [26.0539, 45.9492], "type": "Point"}}