{"type": "Feature", "id": 12515505, "geometry": {"type": "Point", "coordinates": [27.4368, 47.523201]}, "properties": {"woe:id": 12515505, "woe:parent_id": 882120, "woe:name": "Bivolari Airport", "woe:placetype": 14, "woe:placetype_name": "Airport", "woe:lang": "ENG", "iso:country": "RO", "meta:provider": ["geoplanet:7.3.1", "geoplanet:7.3.2", "geoplanet:7.4.0", "geoplanet:7.4.1", "geoplanet:7.5.1", "geoplanet:7.5.2", "geoplanet:7.6.0", "geoplanet:7.8.1", "geoplanet:7.9.0", "geoplanet:7.10.0", "geoplanet:8.0.0", "woeplanet:8.0.0"], "meta:indexed": "2020-08-20T20:26:16.140074", "meta:updated": "2020-10-14T11:54:16.119087", "woe:hierarchy": {"continent": 24865675, "country": 23424933, "town": 0, "planet": 1, "county": 0, "suburb": 0, "state": 2346637, "region": 0, "localadmin": 0}, "woe:timezone_id": 28350892, "woe:hash": "u87w276feybb", "woe:centroid": [27.4368, 47.523201], "geom:latitude": 47.523201, "geom:longitude": 27.4368, "geom:hash": "u87w276feybb", "woe:latitude": 47.523201, "geom:centroid": [27.4368, 47.523201], "woe:longitude": 27.4368, "woe:repo": "woeplanet-airport-ro", "geom:area": 0.0, "woe:scale": 19}}