{"type": "Feature", "id": 12515555, "properties": {"woe:id": 12515555, "woe:parent_id": 876277, "woe:name": "Mureseni Airport", "woe:placetype": 14, "woe:placetype_name": "Airport", "woe:lang": "ENG", "iso:country": "RO", "meta:provider": ["geoplanet:7.3.1", "geoplanet:7.3.2", "geoplanet:7.4.0", "geoplanet:7.4.1", "geoplanet:7.5.1", "geoplanet:7.5.2", "geoplanet:7.6.0", "geoplanet:7.8.1", "geoplanet:7.9.0", "geoplanet:7.10.0", "geoplanet:8.0.0", "woeplanet:8.0.0"], "meta:indexed": "2020-08-20T20:26:16.180067", "meta:updated": "2020-08-22T02:50:11.105780", "woe:hierarchy": {"continent": 24865675, "country": 23424933, "town": 0, "planet": 1, "county": 0, "suburb": 0, "state": 2346640, "region": 0, "localadmin": 0}, "woe:timezone_id": 28350892, "woe:hash": "u832wpcevzyw", "woe:centroid": [24.5238, 46.537399], "geom:latitude": 46.537399, "geom:longitude": 24.5238, "geom:hash": "u832wpcevzyw", "woe:latitude": 46.537399, "geom:centroid": [24.5238, 46.537399], "woe:longitude": 24.5238, "woe:repo": "woeplanet-airport-ro"}, "geometry": {"coordinates": [24.5238, 46.537399], "type": "Point"}}