{"type": "Feature", "id": 12515519, "properties": {"woe:id": 12515519, "woe:parent_id": 869411, "woe:name": "Ciceu Airport", "woe:placetype": 14, "woe:placetype_name": "Airport", "woe:lang": "ENG", "iso:country": "RO", "meta:provider": ["geoplanet:7.3.1", "geoplanet:7.3.2", "geoplanet:7.4.0", "geoplanet:7.4.1", "geoplanet:7.5.1", "geoplanet:7.5.2", "geoplanet:7.6.0", "geoplanet:7.8.1", "geoplanet:7.9.0", "geoplanet:7.10.0", "geoplanet:8.0.0", "woeplanet:8.0.0"], "meta:indexed": "2020-08-20T20:26:16.150469", "meta:updated": "2020-08-22T02:50:11.092236", "woe:hierarchy": {"continent": 24865675, "country": 23424933, "town": 0, "planet": 1, "county": 0, "suburb": 0, "state": 2346634, "region": 0, "localadmin": 0}, "woe:timezone_id": 28350892, "woe:hash": "u84rft597ft5", "woe:centroid": [25.7789, 46.389999], "geom:latitude": 46.389999, "geom:longitude": 25.7789, "geom:hash": "u84rft597ft5", "woe:latitude": 46.389999, "geom:centroid": [25.7789, 46.389999], "woe:longitude": 25.7789, "woe:repo": "woeplanet-airport-ro"}, "geometry": {"coordinates": [25.7789, 46.389999], "type": "Point"}}