{"type": "Feature", "id": 12515530, "properties": {"woe:id": 12515530, "woe:parent_id": 871526, "woe:name": "Dorohoi Northeast Airport", "woe:placetype": 14, "woe:placetype_name": "Airport", "woe:lang": "ENG", "iso:country": "RO", "meta:provider": ["geoplanet:7.3.1", "geoplanet:7.3.2", "geoplanet:7.4.0", "geoplanet:7.4.1", "geoplanet:7.5.1", "geoplanet:7.5.2", "geoplanet:7.6.0", "geoplanet:7.8.1", "geoplanet:7.9.0", "geoplanet:7.10.0", "geoplanet:8.0.0", "woeplanet:8.0.0"], "meta:indexed": "2020-08-20T20:26:16.158800", "meta:updated": "2020-08-22T02:50:11.096676", "woe:hierarchy": {"continent": 24865675, "country": 23424933, "town": 0, "planet": 1, "county": 0, "suburb": 0, "state": 2346621, "region": 0, "localadmin": 0}, "woe:timezone_id": 28350892, "woe:hash": "u8dbcq1wmnhw", "woe:centroid": [26.4244, 47.978401], "geom:latitude": 47.978401, "geom:longitude": 26.4244, "geom:hash": "u8dbcq1wmnhw", "woe:latitude": 47.978401, "geom:centroid": [26.4244, 47.978401], "woe:longitude": 26.4244, "woe:repo": "woeplanet-airport-ro"}, "geometry": {"coordinates": [26.4244, 47.978401], "type": "Point"}}